{"dx":[
[25.00,"CWN","RAB99%20RUS","Beta%20time%20signal,%20ID%20%40xx%3a06%3a00",{"WL":1}]
,[40.00,"CWN","JJY%20JPN","ID%20%40%20xx%3a15%2645%3a40,%20time%20signal",{"WL":1}]
,[49.70,"CW","RTZ%20RUS","time%20signal",{"WL":1}]
,[60.00,"CWN","JJY%20JPN","ID%20%40%20xx%3a15%2645%3a40,%20time%20signal",{"WL":1}]
,[60.00,"CWN","WWVB","no%20ID,%20reversed%20bit%20pattern,%20time%20signal",{"WL":1}]
,[60.00,"CWN","MSF%20GBR","time%20signal",{"WL":1}]
,[66.35,"CW","RBU%20RUS","time%20signal",{"WL":1}]
,[68.00,"CWN","GYN%2fGYN1%20GBR","",{"WL":1}]
,[68.50,"CWN","BPC%20CHN","off%202100-2400Z,%20time%20signal",{"WL":1}]
,[77.50,"CWN","DCF77%20GER","time%20signal",{"WL":1}]
,[136.00,"USB","WSPR","",{"SB":1}]
,[153.00,"AMN","LW%20153","",{"SB":1}]
,[162.00,"AMN","LW%20162","",{"SB":1}]
,[171.00,"AMN","LW%20171","",{"SB":1}]
,[180.00,"AMN","LW%20180","",{"SB":1}]
,[183.00,"AMN","LW%20183","",{"SB":1}]
,[198.00,"AMN","LW%20198","",{"SB":1}]
,[207.00,"AMN","LW%20207","",{"SB":1}]
,[216.00,"AMN","LW%20216","",{"SB":1}]
,[225.00,"AMN","LW%20225","",{"SB":1}]
,[234.00,"AMN","LW%20234","",{"SB":1}]
,[243.00,"AMN","LW%20243","",{"SB":1}]
,[252.00,"AMN","LW%20252","",{"SB":1}]
,[270.00,"AMN","LW%20270","",{"SB":1}]
,[279.00,"AMN","LW%20279","",{"SB":1}]
,[474.20,"USB","WSPR","",{"SB":1}]
,[1836.60,"USB","WSPR","",{"SB":1}]
,[1838.15,"USB","PSK31","",{"SB":1}]
,[2500.00,"AM","WWVH%20%2f%20WWV","time%20signals",{"WL":1}]
,[3330.00,"USB","CHU%20CAN","time%20signal",{"WL":1}]
,[3576.00,"USB","JT65","",{"SB":1}]
,[3580.15,"USB","PSK31","",{"SB":1}]
,[3592.60,"USB","WSPR","",{"SB":1}]
,[4996.00,"CWN","RWM%20RUS","time%20signal,%206AM",{"WL":1}]
,[5000.00,"AM","WWVH%20%2f%20WWV","time%20signals",{"WL":1}]
,[5000.00,"AM","BPM","time%20signal",{"WL":1}]
,[7035.15,"USB","PSK31%20(R1%2f3)","",{"SB":1}]
,[7038.60,"USB","WSPR","",{"SB":1}]
,[7076.00,"USB","JT65","",{"SB":1}]
,[7080.15,"USB","PSK31%20(R2)","",{"SB":1}]
,[7850.00,"USB","CHU%20CAN","time%20signal",{"WL":1}]
,[10000.00,"AM","WWVH%20%2f%20WWV","time%20signals",{"WL":1}]
,[10000.00,"AM","BPM","time%20signal",{"WL":1}]
,[10138.00,"USB","JT65","",{"SB":1}]
,[10138.70,"USB","WSPR","",{"SB":1}]
,[10142.15,"USB","PSK31","",{"SB":1}]
,[14070.15,"USB","PSK31","",{"SB":1}]
,[14076.00,"USB","JT65","",{"SB":1}]
,[14095.60,"USB","WSPR","",{"SB":1}]
,[14100.00,"CW","IBP","NCDXF%2fIARU%20international%20beacon%20project"]
,[14670.00,"USB","CHU%20CAN","time%20signal",{"WL":1}]
,[14996.00,"CWN","RWM%20RUS","time%20signal,%208PM",{"WL":1}]
,[15000.00,"AM","WWVH%20%2f%20WWV","time%20signals",{"WL":1}]
,[15000.00,"AM","BPM","time%20signal",{"WL":1}]
,[18100.15,"USB","PSK31","",{"SB":1}]
,[18104.60,"USB","WSPR","",{"SB":1}]
,[18110.00,"CW","IBP","NCDXF%2fIARU%20international%20beacon%20project"]
,[20000.00,"AM","WWV","time%20signal",{"WL":1}]
,[21076.00,"USB","JT65","",{"SB":1}]
,[21094.60,"USB","WSPR","",{"SB":1}]
,[21150.00,"CW","IBP","NCDXF%2fIARU%20international%20beacon%20project"]
,[24930.00,"CW","IBP","NCDXF%2fIARU%20international%20beacon%20project"]
,[25000.00,"AM","WWV","time%20signal",{"WL":1}]
,[28200.00,"CW","IBP","NCDXF%2fIARU%20international%20beacon%20project"]
]}
